barvikron/__init__.py
barvikron/barvinok.py
barvikron/findiff.py
barvikron/kronecker.py
barvikron/latte.py
barvikron/parfun.py
barvikron/scripts/__init__.py
barvikron/scripts/parallel.py
barvikron/scripts/serial.py
barvikron-0.5.dist-info/METADATA
barvikron-0.5.dist-info/WHEEL
barvikron-0.5.dist-info/entry_points.txt
barvikron-0.5.dist-info/top_level.txt
barvikron-0.5.dist-info/RECORD
