Metadata-Version: 2.1
Name: barvikron
Version: 0.5
Summary: Efficiently compute Kronecker coefficients of bounded height (using the algorithm of arXiv:1204.4379).
Author-email: Michael Walter <michael.walter@rub.de>
License: MIT
Project-URL: Homepage, https://github.com/qi-rub/barvikron
Project-URL: Bug Tracker, https://github.com/qi-rub/barvikron/issues
Classifier: Development Status :: 4 - Beta
Classifier: Environment :: Console
Classifier: License :: OSI Approved :: MIT License
Classifier: Operating System :: OS Independent
Classifier: Programming Language :: Python :: 3
Requires-Python: >=3.9
Requires-Dist: click
Requires-Dist: numpy
Requires-Dist: whichcraft
Provides-Extra: dev
Requires-Dist: black ; extra == 'dev'
Requires-Dist: build ; extra == 'dev'
Requires-Dist: pytest ; extra == 'dev'
Requires-Dist: pytest-clarity ; extra == 'dev'
Requires-Dist: pytest-sugar ; extra == 'dev'
Requires-Dist: twine ; extra == 'dev'
